{"demo":[{"group":312,"value":287},{"group":313,"value":872},{"group":314,"value":373},{"group":315,"value":1072},{"group":316,"value":1625},{"group":317,"value":1132}],"population":5361,"cutter":{"SOC":{"id":"1","name":"Social Resilience","sources":[{"id":"11","name":"Educational Equity","states":0.086,"us":0.074,"county":0.0612},{"id":"12","name":"Age","states":0.678,"us":0.721,"county":0.6537},{"id":"13","name":"Transportation Access","states":0.948,"us":0.916,"county":0.9356},{"id":"14","name":"Communication Capacity","states":0.919,"us":0.873,"county":0.9224},{"id":"15","name":"Language Capacity","states":0.949,"us":0.903,"county":0.9628},{"id":"16","name":"Special Needs","states":0.774,"us":0.657,"county":0.7434},{"id":"17","name":"Health Coverage","states":0.852,"us":0.762,"county":0.9554}],"aggregate":{"us":0.700857142857143,"state":0.7437142857142858,"county":0.7477857142857144}},"ECON":{"id":"2","name":"Economic Resilience","sources":[{"id":"21","name":"Housing Capital","states":0.636,"us":0.641,"county":0.66},{"id":"22","name":"Employment","states":0.601,"us":0.489,"county":0.6287},{"id":"23","name":"Income and Equality (GINI Coeffecient)","states":0.551,"us":0.598,"county":0.6902},{"id":"24","name":"Single Sector Employment Dependence","states":0.944,"us":0.982,"county":1},{"id":"25","name":"Employment (Female)","states":0.619,"us":0.536,"county":0.6162},{"id":"26","name":"Business Size","states":0.002,"us":0.007,"county":0},{"id":"27","name":"Health Access","states":0.116,"us":0.125,"county":0.1649}],"aggregate":{"us":0.4825714285714286,"state":0.49557142857142855,"county":0.5371428571428571}},"INST":{"id":"3","name":"Institutional Resilience","sources":[{"id":"31","name":"Mitigation - Hazard Mitigation Plan Coverage","us":null,"county":null},{"id":"32","name":"Flood Coverage","states":0.008,"us":0.014,"county":0.0169},{"id":"33","name":"Municipal Services","us":null,"county":null},{"id":"34","name":"Mitigation - CRS Flood","us":null,"county":null},{"id":"35","name":"Political Fragmentation","us":null,"county":null},{"id":"36","name":"Previous Disaster Experience","states":0.31,"us":0.211,"county":0.4154},{"id":"37","name":"Mitigation and Social Connectivity","us":null,"county":null},{"id":"38","name":"Mitigation - Storm Ready Communities","us":null,"county":null}],"aggregate":{"us":0.1125,"state":0.159,"county":0.21615}},"IHFR":{"id":"4","name":"Infrastructure Resilience","sources":[{"id":"41","name":"Housing Type","states":0.853,"us":0.797,"county":0.9341},{"id":"42","name":"Shelter Capacity","states":0.177,"us":0.184,"county":0.0753},{"id":"43","name":"Medical Capacity","states":0.017,"us":0.003,"county":0.0015},{"id":"44","name":"Access/Evacuation Potential","states":0.004,"us":0.009,"county":0.0027},{"id":"45","name":"Housing Age","states":0.28,"us":0.459,"county":0.2735},{"id":"46","name":"Sheltering Need","states":0,"us":0.002,"county":0.0002},{"id":"47","name":"Recovery (Schools)","states":0,"us":0.003,"county":null}],"aggregate":{"us":0.24233333333333337,"state":0.22183333333333333,"county":0.21455000000000002}},"COMM":{"id":"5","name":"Community Capital","sources":[{"id":"51","name":"Place Attachment - Migration","states":0.966,"us":0.912,"county":0.9712},{"id":"52","name":"Place Attachment - Born","states":0.718,"us":0.671,"county":0.72},{"id":"53","name":"Political Engagement","states":0.462,"us":0.404,"county":0.3865},{"id":"54","name":"Social Capital - Religion","states":0.274,"us":0.186,"county":0.2842},{"id":"55","name":"Social Capital - Civic Involvement","states":0.252,"us":0.089,"county":1},{"id":"56","name":"Social Capital - Advocacy","states":0.011,"us":0.016,"county":0.1517},{"id":"57","name":"Innovation","states":0.044,"us":0.034,"county":0.0298}],"aggregate":{"us":0.33028571428571424,"state":0.38957142857142857,"county":0.5061999999999999}},"FLOR":{"id":"100","name":"Special/Custom","sources":[{"id":"101","name":"Business Vulnerability","us":null,"county":null},{"id":"102","name":"Flood Zone","us":null,"county":null},{"id":"103","name":"Commuting","us":null,"county":null},{"id":"104","name":"Housing Construction","us":null,"county":null},{"id":"105","name":"Second Stage Businesses","states":0.424,"us":0.487,"county":0.3749},{"id":"106","name":"Households with Broadband Access","states":0.665,"us":0.645,"county":0.6945}],"aggregate":{"us":0.5660000000000001,"state":0.5445,"county":0.5347}}},"statefips":"38","countyfips":"073","county":"Ransom","state":"North Dakota","area":862.357,"eda2018":[],"disasters":[{"disasterNumber":195,"ihProgramDeclared":0,"iaProgramDeclared":1,"paProgramDeclared":1,"hmProgramDeclared":0,"state":"ND","statefips":"38","declarationDate":"1965-05-10T00:00:00.000Z","fyDeclared":"1965","disasterType":"DR","incidentType":"Flood","title":"FLOODING","incidentBeginDate":"1965-05-10T00:00:00.000Z","incidentEndDate":"1965-05-10T00:00:00.000Z","disasterCloseOutDate":"1967-11-07T00:00:00.000Z","declaredCountyArea":"Ransom (County)","placeCode":"99073","countyfips":"073","hash":"fd7abd9bf5431a7480f11d8a62e554eb","latRefresh":"2019-07-26T18:08:57.889Z"},{"disasterNumber":216,"ihProgramDeclared":0,"iaProgramDeclared":1,"paProgramDeclared":1,"hmProgramDeclared":0,"state":"ND","statefips":"38","declarationDate":"1966-03-23T00:00:00.000Z","fyDeclared":"1966","disasterType":"DR","incidentType":"Flood","title":"FLOODING","incidentBeginDate":"1966-03-23T00:00:00.000Z","incidentEndDate":"1966-03-23T00:00:00.000Z","disasterCloseOutDate":"1968-08-12T00:00:00.000Z","declaredCountyArea":"Ransom (County)","placeCode":"99073","countyfips":"073","hash":"6fef84893bd388e40a9b6eaf26c50e5e","latRefresh":"2019-07-26T18:08:58.292Z"},{"disasterNumber":256,"ihProgramDeclared":0,"iaProgramDeclared":1,"paProgramDeclared":1,"hmProgramDeclared":0,"state":"ND","statefips":"38","declarationDate":"1969-04-18T00:00:00.000Z","fyDeclared":"1969","disasterType":"DR","incidentType":"Flood","title":"FLOODING","incidentBeginDate":"1969-04-18T00:00:00.000Z","incidentEndDate":"1969-04-18T00:00:00.000Z","disasterCloseOutDate":"1972-11-28T00:00:00.000Z","declaredCountyArea":"Ransom (County)","placeCode":"99073","countyfips":"073","hash":"f516e3dde12996a3afacdfa34c3ae552","latRefresh":"2019-07-26T18:08:58.956Z"},{"disasterNumber":287,"ihProgramDeclared":0,"iaProgramDeclared":1,"paProgramDeclared":1,"hmProgramDeclared":0,"state":"ND","statefips":"38","declarationDate":"1970-06-05T00:00:00.000Z","fyDeclared":"1970","disasterType":"DR","incidentType":"Flood","title":"SEVERE STORMS & FLOODING","incidentBeginDate":"1970-06-05T00:00:00.000Z","incidentEndDate":"1970-06-05T00:00:00.000Z","disasterCloseOutDate":"1972-05-16T00:00:00.000Z","declaredCountyArea":"Ransom (County)","placeCode":"99073","countyfips":"073","hash":"aed2128e1dba873474cbaf3e5dbcd9cf","latRefresh":"2019-07-26T18:08:58.962Z"},{"disasterNumber":475,"ihProgramDeclared":0,"iaProgramDeclared":1,"paProgramDeclared":1,"hmProgramDeclared":0,"state":"ND","statefips":"38","declarationDate":"1975-07-11T00:00:00.000Z","fyDeclared":"1975","disasterType":"DR","incidentType":"Flood","title":"SEVERE STORMS & FLOODING","incidentBeginDate":"1975-07-11T00:00:00.000Z","incidentEndDate":"1975-07-11T00:00:00.000Z","disasterCloseOutDate":"1981-04-16T00:00:00.000Z","declaredCountyArea":"Ransom (County)","placeCode":"99073","countyfips":"073","hash":"55b59a838b7cd31ef119e4d68561fbb8","latRefresh":"2019-07-26T18:09:01.032Z"},{"disasterNumber":3016,"ihProgramDeclared":0,"iaProgramDeclared":0,"paProgramDeclared":1,"hmProgramDeclared":0,"state":"ND","statefips":"38","declarationDate":"1976-07-21T00:00:00.000Z","fyDeclared":"1976","disasterType":"EM","incidentType":"Drought","title":"DROUGHT","incidentBeginDate":"1976-07-21T00:00:00.000Z","incidentEndDate":"1976-07-21T00:00:00.000Z","disasterCloseOutDate":"1979-01-29T00:00:00.000Z","declaredCountyArea":"Ransom (County)","placeCode":"99073","countyfips":"073","hash":"d83db49b3564bcf5c89efba5d05a90c1","latRefresh":"2019-07-26T18:09:21.521Z"},{"disasterNumber":581,"ihProgramDeclared":0,"iaProgramDeclared":1,"paProgramDeclared":1,"hmProgramDeclared":0,"state":"ND","statefips":"38","declarationDate":"1979-04-26T00:00:00.000Z","fyDeclared":"1979","disasterType":"DR","incidentType":"Flood","title":"SEVERE STORMS, SNOWMELT & FLOODING","incidentBeginDate":"1979-04-26T00:00:00.000Z","incidentEndDate":"1979-04-26T00:00:00.000Z","disasterCloseOutDate":"1984-10-24T00:00:00.000Z","declaredCountyArea":"Ransom (County)","placeCode":"99073","countyfips":"073","hash":"4700c0da1ec27eeb62adeedcfee708fb","latRefresh":"2019-07-26T18:09:01.954Z"},{"disasterNumber":1001,"ihProgramDeclared":0,"iaProgramDeclared":1,"paProgramDeclared":1,"hmProgramDeclared":0,"state":"ND","statefips":"38","declarationDate":"1993-07-26T00:00:00.000Z","fyDeclared":"1993","disasterType":"DR","incidentType":"Flood","title":"SEVERE STORMS & FLOODING","incidentBeginDate":"1993-06-22T00:00:00.000Z","incidentEndDate":"1993-09-24T00:00:00.000Z","disasterCloseOutDate":"2006-03-06T00:00:00.000Z","declaredCountyArea":"Ransom (County)","placeCode":"99073","countyfips":"073","hash":"85f4c01004ac0117a428a67d030c38c9","latRefresh":"2019-07-26T18:09:05.534Z"},{"disasterNumber":1050,"ihProgramDeclared":0,"iaProgramDeclared":1,"paProgramDeclared":1,"hmProgramDeclared":0,"state":"ND","statefips":"38","declarationDate":"1995-05-16T00:00:00.000Z","fyDeclared":"1995","disasterType":"DR","incidentType":"Severe Storm(s)","title":"SEVERE STORMS, FLOODING, AND GROUND SATURATION","incidentBeginDate":"1995-03-01T00:00:00.000Z","incidentEndDate":"1995-07-05T00:00:00.000Z","disasterCloseOutDate":"2001-07-16T00:00:00.000Z","declaredCountyArea":"Ransom (County)","placeCode":"99073","countyfips":"073","hash":"db6baeb5233cd0aa0909938e5fc87918","latRefresh":"2019-07-26T18:09:06.236Z"},{"disasterNumber":1118,"ihProgramDeclared":0,"iaProgramDeclared":0,"paProgramDeclared":1,"hmProgramDeclared":0,"state":"ND","statefips":"38","declarationDate":"1996-06-05T00:00:00.000Z","fyDeclared":"1996","disasterType":"DR","incidentType":"Severe Storm(s)","title":"SEVERE STORMS,FLOODING, &  ICE JAMS","incidentBeginDate":"1996-03-12T00:00:00.000Z","incidentEndDate":"1996-06-21T00:00:00.000Z","disasterCloseOutDate":"2002-07-19T00:00:00.000Z","declaredCountyArea":"Ransom (County)","placeCode":"99073","countyfips":"073","hash":"f1e24a49c19d373eb47af02da29475d8","latRefresh":"2019-07-26T18:09:07.412Z"},{"disasterNumber":1157,"ihProgramDeclared":0,"iaProgramDeclared":0,"paProgramDeclared":1,"hmProgramDeclared":1,"state":"ND","statefips":"38","declarationDate":"1997-01-12T00:00:00.000Z","fyDeclared":"1997","disasterType":"DR","incidentType":"Severe Storm(s)","title":"SEVERE WINTER STORMS AND BLIZZARD CONDITIONS","incidentBeginDate":"1997-01-03T00:00:00.000Z","incidentEndDate":"1997-01-31T00:00:00.000Z","disasterCloseOutDate":"1999-01-21T00:00:00.000Z","declaredCountyArea":"Ransom (County)","placeCode":"99073","countyfips":"073","hash":"50f585de96d3b329a22531f4a50ad6e9","latRefresh":"2019-07-26T18:09:07.906Z"},{"disasterNumber":1174,"ihProgramDeclared":0,"iaProgramDeclared":1,"paProgramDeclared":1,"hmProgramDeclared":0,"state":"ND","statefips":"38","declarationDate":"1997-04-07T00:00:00.000Z","fyDeclared":"1997","disasterType":"DR","incidentType":"Flood","title":"SEVERE FLOODING,SEVERE WINTER STORMS, SNOWMELT, SPRING RAINS","incidentBeginDate":"1997-02-28T00:00:00.000Z","incidentEndDate":"1997-05-24T00:00:00.000Z","disasterCloseOutDate":"2012-07-31T00:00:00.000Z","declaredCountyArea":"Ransom (County)","placeCode":"99073","countyfips":"073","hash":"79b21bbf1761016a638928fe4d92ed23","latRefresh":"2019-07-26T18:09:08.277Z"},{"disasterNumber":1220,"ihProgramDeclared":0,"iaProgramDeclared":1,"paProgramDeclared":1,"hmProgramDeclared":0,"state":"ND","statefips":"38","declarationDate":"1998-06-15T00:00:00.000Z","fyDeclared":"1998","disasterType":"DR","incidentType":"Flood","title":"FLOODING, GROUND SATURATION,SEVERE STORMS","incidentBeginDate":"1998-03-02T00:00:00.000Z","incidentEndDate":"1998-07-18T00:00:00.000Z","disasterCloseOutDate":"2011-08-01T00:00:00.000Z","declaredCountyArea":"Ransom (County)","placeCode":"99073","countyfips":"073","hash":"cae856a262925a1988945f9f95648460","latRefresh":"2019-07-26T18:09:08.894Z"},{"disasterNumber":1279,"ihProgramDeclared":0,"iaProgramDeclared":1,"paProgramDeclared":1,"hmProgramDeclared":1,"state":"ND","statefips":"38","declarationDate":"1999-06-08T16:45:00.000Z","fyDeclared":"1999","disasterType":"DR","incidentType":"Flood","title":"SEVERE STORMS, FLOODING, SNOW, ICE, GROUND SATURATION, LANSLIDES, MUDSLIDES, AND TOR","incidentBeginDate":"1999-03-01T08:00:00.000Z","incidentEndDate":"1999-07-19T00:00:00.000Z","disasterCloseOutDate":"2010-06-24T00:00:00.000Z","declaredCountyArea":"Ransom (County)","placeCode":"99073","countyfips":"073","hash":"697fe32982ccbcfc3d1986c7f2635ce9","latRefresh":"2019-07-26T18:09:09.845Z"},{"disasterNumber":1334,"ihProgramDeclared":0,"iaProgramDeclared":1,"paProgramDeclared":1,"hmProgramDeclared":0,"state":"ND","statefips":"38","declarationDate":"2000-06-27T20:54:32.000Z","fyDeclared":"2000","disasterType":"DR","incidentType":"Severe Storm(s)","title":"SEVERE STORMS, FLOODING AND GROUND SATURATION","incidentBeginDate":"2000-04-05T09:40:00.000Z","incidentEndDate":"2000-08-12T00:00:00.000Z","disasterCloseOutDate":"2010-08-10T00:00:00.000Z","declaredCountyArea":"Ransom (County)","placeCode":"99073","countyfips":"073","hash":"3f43fde33bd1cb16470ce514e72aabba","latRefresh":"2019-07-26T18:09:10.497Z"},{"disasterNumber":1376,"ihProgramDeclared":0,"iaProgramDeclared":0,"paProgramDeclared":1,"hmProgramDeclared":1,"state":"ND","statefips":"38","declarationDate":"2001-05-28T00:00:00.000Z","fyDeclared":"2001","disasterType":"DR","incidentType":"Flood","title":"SEVERE STORMS, FLOODING, & GROUND SATURATION","incidentBeginDate":"2001-03-01T14:00:00.000Z","incidentEndDate":"2001-08-09T00:00:00.000Z","disasterCloseOutDate":"2012-04-04T00:00:00.000Z","declaredCountyArea":"Ransom (County)","placeCode":"99073","countyfips":"073","hash":"56104d54d293a5a14e72f99c82c4ce60","latRefresh":"2019-07-26T18:09:11.138Z"},{"disasterNumber":1597,"ihProgramDeclared":0,"iaProgramDeclared":0,"paProgramDeclared":1,"hmProgramDeclared":1,"state":"ND","statefips":"38","declarationDate":"2005-07-22T18:51:00.000Z","fyDeclared":"2005","disasterType":"DR","incidentType":"Severe Storm(s)","title":"SEVERE STORMS, FLOODING, AND GROUND SATURATION","incidentBeginDate":"2005-06-01T00:00:00.000Z","incidentEndDate":"2005-07-07T00:00:00.000Z","disasterCloseOutDate":"2012-08-08T00:00:00.000Z","declaredCountyArea":"Ransom (County)","placeCode":"99073","countyfips":"073","hash":"0357a928d303ba1451826d2ac5ba87d5","latRefresh":"2019-07-26T18:09:14.747Z"},{"disasterNumber":3247,"ihProgramDeclared":0,"iaProgramDeclared":0,"paProgramDeclared":1,"hmProgramDeclared":0,"state":"ND","statefips":"38","declarationDate":"2005-09-13T13:34:00.000Z","fyDeclared":"2005","disasterType":"EM","incidentType":"Coastal Storm","title":"HURRICANE KATRINA EVACUATION","incidentBeginDate":"2005-08-29T10:00:00.000Z","incidentEndDate":"2005-10-01T08:55:00.000Z","disasterCloseOutDate":"2008-09-30T00:00:00.000Z","declaredCountyArea":"Ransom (County)","placeCode":"99073","countyfips":"073","hash":"5747a7b67a0f38e9f019ede9ca52f6be","latRefresh":"2019-07-26T18:09:26.841Z"},{"disasterNumber":1621,"ihProgramDeclared":0,"iaProgramDeclared":0,"paProgramDeclared":1,"hmProgramDeclared":1,"state":"ND","statefips":"38","declarationDate":"2006-01-04T18:42:00.000Z","fyDeclared":"2006","disasterType":"DR","incidentType":"Severe Storm(s)","title":"SEVERE WINTER STORM","incidentBeginDate":"2005-11-27T10:00:00.000Z","incidentEndDate":"2005-11-30T00:00:00.000Z","disasterCloseOutDate":"2012-08-08T00:00:00.000Z","declaredCountyArea":"Ransom (County)","placeCode":"99073","countyfips":"073","hash":"ab2743d4862587e80dee92079dddb38c","latRefresh":"2019-07-26T18:09:15.226Z"},{"disasterNumber":1645,"ihProgramDeclared":0,"iaProgramDeclared":0,"paProgramDeclared":1,"hmProgramDeclared":1,"state":"ND","statefips":"38","declarationDate":"2006-06-05T19:15:00.000Z","fyDeclared":"2006","disasterType":"DR","incidentType":"Severe Storm(s)","title":"SEVERE STORMS, FLOODING, AND GROUND SATURATION","incidentBeginDate":"2006-03-30T19:00:00.000Z","incidentEndDate":"2006-04-30T23:00:00.000Z","disasterCloseOutDate":"2012-11-15T00:00:00.000Z","declaredCountyArea":"Ransom (County)","placeCode":"99073","countyfips":"073","hash":"fde8390ee6d2180706645e7055163975","latRefresh":"2019-07-26T18:09:15.660Z"},{"disasterNumber":1713,"ihProgramDeclared":0,"iaProgramDeclared":0,"paProgramDeclared":1,"hmProgramDeclared":1,"state":"ND","statefips":"38","declarationDate":"2007-07-17T17:40:00.000Z","fyDeclared":"2007","disasterType":"DR","incidentType":"Severe Storm(s)","title":"SEVERE STORMS AND FLOODING","incidentBeginDate":"2007-06-02T10:52:00.000Z","incidentEndDate":"2007-06-18T00:00:00.000Z","disasterCloseOutDate":"2013-11-06T23:59:00.000Z","declaredCountyArea":"Ransom (County)","placeCode":"99073","countyfips":"073","hash":"1cda8887c913d1aad51fff28b821819c","latRefresh":"2019-07-26T18:09:16.438Z"},{"disasterNumber":1829,"ihProgramDeclared":1,"iaProgramDeclared":0,"paProgramDeclared":1,"hmProgramDeclared":1,"state":"ND","statefips":"38","declarationDate":"2009-03-24T22:30:00.000Z","fyDeclared":"2009","disasterType":"DR","incidentType":"Severe Storm(s)","title":"SEVERE STORMS AND FLOODING","incidentBeginDate":"2009-03-13T09:00:00.000Z","incidentEndDate":"2009-08-10T00:00:00.000Z","disasterCloseOutDate":"2018-05-02T23:59:00.000Z","declaredCountyArea":"Ransom (County)","placeCode":"99073","countyfips":"073","hash":"5bcc2f355f7d0b1c926d980f5a9d8dd2","latRefresh":"2019-07-26T18:09:17.979Z"},{"disasterNumber":1879,"ihProgramDeclared":0,"iaProgramDeclared":0,"paProgramDeclared":1,"hmProgramDeclared":1,"state":"ND","statefips":"38","declarationDate":"2010-02-26T16:25:00.000Z","fyDeclared":"2010","disasterType":"DR","incidentType":"Severe Storm(s)","title":"SEVERE WINTER STORM","incidentBeginDate":"2010-01-20T00:00:00.000Z","incidentEndDate":"2010-01-25T12:00:00.000Z","disasterCloseOutDate":"2015-03-18T23:59:00.000Z","declaredCountyArea":"Ransom (County)","placeCode":"99073","countyfips":"073","hash":"62d9838ca5bd2e966f7eb36638afe9aa","latRefresh":"2019-07-26T18:09:18.708Z"},{"disasterNumber":3309,"ihProgramDeclared":0,"iaProgramDeclared":0,"paProgramDeclared":1,"hmProgramDeclared":0,"state":"ND","statefips":"38","declarationDate":"2010-03-14T00:00:00.000Z","fyDeclared":"2010","disasterType":"EM","incidentType":"Flood","title":"FLOODING","incidentBeginDate":"2010-02-26T00:00:00.000Z","incidentEndDate":"2010-04-30T00:00:00.000Z","disasterCloseOutDate":"2013-11-19T23:59:00.000Z","declaredCountyArea":"Ransom (County)","placeCode":"99073","countyfips":"073","hash":"daeae6823cef68433a56a03ad3c6fb06","latRefresh":"2019-07-26T18:09:29.802Z"},{"disasterNumber":1907,"ihProgramDeclared":0,"iaProgramDeclared":0,"paProgramDeclared":1,"hmProgramDeclared":1,"state":"ND","statefips":"38","declarationDate":"2010-04-30T17:37:00.000Z","fyDeclared":"2010","disasterType":"DR","incidentType":"Flood","title":"FLOODING","incidentBeginDate":"2010-02-26T00:00:00.000Z","incidentEndDate":"2010-07-15T12:00:00.000Z","disasterCloseOutDate":"2018-07-31T23:59:00.000Z","declaredCountyArea":"Ransom (County)","placeCode":"99073","countyfips":"073","hash":"4cadfdcf1fcfc4c23e8c58a499ff2ce3","latRefresh":"2019-07-26T18:09:19.041Z"},{"disasterNumber":3318,"ihProgramDeclared":0,"iaProgramDeclared":0,"paProgramDeclared":1,"hmProgramDeclared":0,"state":"ND","statefips":"38","declarationDate":"2011-04-07T20:00:00.000Z","fyDeclared":"2011","disasterType":"EM","incidentType":"Flood","title":"FLOODING","incidentBeginDate":"2011-04-05T00:00:00.000Z","incidentEndDate":"2011-07-01T00:00:00.000Z","disasterCloseOutDate":"2013-08-02T00:00:00.000Z","declaredCountyArea":"Ransom (County)","placeCode":"99073","countyfips":"073","hash":"7981d09f9bdf46976833b41ce072e45e","latRefresh":"2019-07-26T18:09:30.024Z"},{"disasterNumber":1981,"ihProgramDeclared":0,"iaProgramDeclared":0,"paProgramDeclared":1,"hmProgramDeclared":1,"state":"ND","statefips":"38","declarationDate":"2011-05-10T19:00:00.000Z","fyDeclared":"2011","disasterType":"DR","incidentType":"Flood","title":"FLOODING","incidentBeginDate":"2011-02-14T00:00:00.000Z","incidentEndDate":"2011-07-20T00:00:00.000Z","disasterCloseOutDate":null,"declaredCountyArea":"Ransom (County)","placeCode":"99073","countyfips":"073","hash":"c8bf9338f0dc1b526d93ba7a344c62ab","latRefresh":"2019-10-10T19:56:56.070Z"},{"disasterNumber":4444,"ihProgramDeclared":0,"iaProgramDeclared":0,"paProgramDeclared":1,"hmProgramDeclared":1,"state":"ND","statefips":"38","declarationDate":"2019-06-12T13:38:00.000Z","fyDeclared":"2019","disasterType":"DR","incidentType":"Flood","title":"FLOODING","incidentBeginDate":"2019-03-21T00:00:00.000Z","incidentEndDate":"2019-04-28T23:59:00.000Z","disasterCloseOutDate":"","declaredCountyArea":"Ransom (County)","placeCode":"99073","countyfips":"073","hash":"575eb9d3d687284141441f441e4bf477","latRefresh":"2019-10-10T19:57:09.008Z"},{"disasterNumber":3477,"ihProgramDeclared":0,"iaProgramDeclared":0,"paProgramDeclared":1,"hmProgramDeclared":0,"state":"ND","statefips":"38","declarationDate":"2020-03-13T16:00:00.000Z","fyDeclared":"2020","disasterType":"EM","incidentType":"Biological","title":"COVID-19","incidentBeginDate":"2020-01-20T14:00:00.000Z","incidentEndDate":"","disasterCloseOutDate":"","declaredCountyArea":"Ransom (County)","placeCode":"99073","countyfips":"073","hash":"17c4f7a31a29da92ee3915d019cfe5a7","latRefresh":"2020-03-16T15:21:00.269Z"},{"disasterNumber":4509,"ihProgramDeclared":0,"iaProgramDeclared":0,"paProgramDeclared":1,"hmProgramDeclared":0,"state":"ND","statefips":"38","declarationDate":"2020-04-01T12:35:00.000Z","fyDeclared":"2020","disasterType":"DR","incidentType":"Biological","title":"COVID-19 PANDEMIC","incidentBeginDate":"2020-01-20T14:00:00.000Z","incidentEndDate":"","disasterCloseOutDate":"","declaredCountyArea":"Ransom (County)","placeCode":"99073","countyfips":"073","hash":"c0d14e9d98fffa83614d872dcee2b2cf","latRefresh":"2020-04-01T17:40:59.917Z"}],"storms":{"Tornado":{"1957":1,"1959":1,"1960":1,"1965":1,"1966":1,"1967":2,"1969":1,"1970":2,"1973":1,"1980":1,"1982":1,"1987":1,"1997":1,"1998":2,"2007":3,"2008":1,"2010":3},"Hail":{"1959":1,"1966":1,"1967":1,"1973":1,"1977":1,"1980":8,"1982":1,"1983":1,"1985":5,"1986":2,"1987":1,"1988":2,"1989":2,"1990":1,"1991":1,"1994":2,"1996":1,"1997":1,"1998":12,"2007":3,"2008":7,"2009":5,"2010":7,"2011":3,"2012":7,"2013":4,"2014":3,"2015":5,"2016":3,"2017":1,"2018":4,"2019":1},"Thunderstorm Wind":{"1959":1,"1967":1,"1970":1,"1971":1,"1974":1,"1975":1,"1977":3,"1978":2,"1979":1,"1980":2,"1983":1,"1985":1,"1986":1,"1987":1,"1988":1,"1989":2,"1990":3,"1992":1,"1995":3,"1997":2,"1998":5,"2007":8,"2008":1,"2009":1,"2010":2,"2011":3,"2012":2,"2015":2,"2016":7,"2017":3,"2018":3},"Funnel Cloud":{"1998":1,"2008":1,"2010":1,"2011":4,"2018":1},"Flood":{"2007":3,"2009":3,"2010":2,"2011":1,"2019":1},"Flash Flood":{"2007":1,"2009":1,"2010":2,"2013":2,"2015":1,"2016":1},"Heavy Rain":{"2011":1}},"bvis":[{"year":2012,"county":38073,"estab_total":198,"estab_vuln_total":16,"mm_employees":1697,"emp_vuln_total":53},{"year":2013,"county":38073,"estab_total":194,"estab_vuln_total":16,"mm_employees":1757,"emp_vuln_total":78},{"year":2014,"county":38073,"estab_total":188,"estab_vuln_total":16,"mm_employees":1675,"emp_vuln_total":75},{"year":2015,"county":38073,"estab_total":193,"estab_vuln_total":16,"mm_employees":1541,"emp_vuln_total":107},{"year":2016,"county":38073,"estab_total":199,"estab_vuln_total":18,"mm_employees":1493,"emp_vuln_total":105},{"year":2017,"county":38073,"estab_total":207,"estab_vuln_total":16,"mm_employees":1561,"emp_vuln_total":108}]}